ccu/__about__.py
ccu/__init__.py
ccu/__main__.py
ccu/py.typed
ccu/settings.py
ccu/_cli/__init__.py
ccu/_cli/_init.py
ccu/_cli/_main.py
ccu/_cli/_utils.py
ccu/adsorption/__init__.py
ccu/adsorption/_cli.py
ccu/adsorption/adsorbates.py
ccu/adsorption/complexes.py
ccu/adsorption/orientation.py
ccu/adsorption/sites.py
ccu/fancyplots/__init__.py
ccu/fancyplots/_cli.py
ccu/fancyplots/data.py
ccu/fancyplots/plotting.py
ccu/fancyplots/styles.py
ccu/fancyplots/validation.py
ccu/fancyplots/_gui/__init__.py
ccu/fancyplots/_gui/annotation.py
ccu/fancyplots/_gui/energy.py
ccu/fancyplots/_gui/fed.py
ccu/fancyplots/_gui/footer.py
ccu/fancyplots/_gui/formatting.py
ccu/fancyplots/_gui/frames.py
ccu/fancyplots/_gui/instructions.py
ccu/fancyplots/_gui/mechanism.py
ccu/fancyplots/_gui/menu.py
ccu/fancyplots/_gui/palette.py
ccu/fancyplots/_gui/root.py
ccu/fancyplots/_gui/tooltip.py
ccu/fancyplots/_gui/utils.py
ccu/fancyplots/images/color_palette.png
ccu/fancyplots/images/fancy_plots_tutorial.png
ccu/pop/__init__.py
ccu/pop/_cli.py
ccu/pop/bader.py
ccu/structure/__init__.py
ccu/structure/_cli.py
ccu/structure/axisfinder.py
ccu/structure/comparator.py
ccu/structure/defects.py
ccu/structure/fingerprint.py
ccu/structure/geometry.py
ccu/structure/resizecell.py
ccu/structure/symmetry.py
ccu/thermo/__init__.py
ccu/thermo/_cli.py
ccu/thermo/chempot.py
ccu/thermo/gibbs.py
ccu/thermo/_chempot_data/b_data.csv
ccu/thermo/_chempot_data/m_data.csv
ccu/thermo/_chempot_data/param_data.csv
ccu/thermo/_chempot_data/zpe_data.csv
ccu/workflows/__init__.py
ccu/workflows/calculation.py
ccu/workflows/hubbard_u.py
ccu/workflows/infrared.py
ccu/workflows/vcdd.py
ccu/workflows/vibration.py
comp_chem_utils-0.0.6.dist-info/METADATA
comp_chem_utils-0.0.6.dist-info/WHEEL
comp_chem_utils-0.0.6.dist-info/entry_points.txt
comp_chem_utils-0.0.6.dist-info/licenses/AUTHORS.rst
comp_chem_utils-0.0.6.dist-info/licenses/LICENSE
comp_chem_utils-0.0.6.dist-info/RECORD
