Metadata-Version: 2.4
Name: comp-chem-utils
Version: 0.0.6
Summary: Utilities for computational chemistry.
Project-URL: Source, https://gitlab.com/ugognw/python-comp-chem-utils
Project-URL: Documentation, https://python-comp-chem-utils.readthedocs.io/
Project-URL: Changelog, https://gitlab.com/ugognw/python-comp-chem-utils/-/blob/main/CHANGELOG.rst
Project-URL: Issues, https://gitlab.com/ugognw/python-comp-chem-utils/-/issues
Author-email: Ugochukwu Nwosu <ugognw@gmail.com>, Tiago Joao Ferreira Goncalves <tiagojoaog@gmail.com>
License-File: AUTHORS.rst
License-File: LICENSE
Keywords: catalysis,comp-chem-utils,computational chemistry
Classifier: Development Status :: 3 - Alpha
Classifier: Intended Audience :: Developers
Classifier: Intended Audience :: Science/Research
Classifier: License :: OSI Approved :: MIT License
Classifier: Operating System :: POSIX
Classifier: Operating System :: Unix
Classifier: Programming Language :: Python
Classifier: Programming Language :: Python :: 3
Classifier: Programming Language :: Python :: 3 :: Only
Classifier: Programming Language :: Python :: 3.10
Classifier: Programming Language :: Python :: 3.11
Classifier: Programming Language :: Python :: 3.12
Classifier: Programming Language :: Python :: 3.13
Classifier: Programming Language :: Python :: Implementation :: CPython
Classifier: Programming Language :: Python :: Implementation :: PyPy
Classifier: Topic :: Scientific/Engineering :: Chemistry
Classifier: Topic :: Scientific/Engineering :: Physics
Classifier: Topic :: Software Development :: Libraries :: Python Modules
Requires-Python: >=3.10
Requires-Dist: ase>=3.23.0
Requires-Dist: click>=8.1.8
Requires-Dist: matplotlib>=3.10.0
Requires-Dist: numpy<2.0.0,>=1.23.1
Requires-Dist: pillow>=10.1
Requires-Dist: pydantic-settings>=2.0
Requires-Dist: pydantic>=2.5.0
Requires-Dist: pymatgen>=2023.9.2
Requires-Dist: scipy>=1.10.1
Provides-Extra: dev
Requires-Dist: bump-my-version>=1.2.0; extra == 'dev'
Requires-Dist: mypy>=1.17.0; extra == 'dev'
Requires-Dist: pre-commit>=2.20.0; extra == 'dev'
Requires-Dist: ruff>=0.12.3; extra == 'dev'
Provides-Extra: docs
Requires-Dist: furo>=2024.04.27; extra == 'docs'
Requires-Dist: sphinx-autobuild>=2024.10.03; extra == 'docs'
Requires-Dist: sphinx-click>=5.0.1; extra == 'docs'
Requires-Dist: sphinx-copybutton>=0.5.2; extra == 'docs'
Requires-Dist: sphinx-notfound-page>=1.1.0; extra == 'docs'
Requires-Dist: sphinx>=8.0.0; extra == 'docs'
Provides-Extra: test
Requires-Dist: pytest-cov>=6.0.0; extra == 'test'
Requires-Dist: pytest-datadir>=1.7.0; extra == 'test'
Requires-Dist: pytest-xdist>=3.8.0; extra == 'test'
Requires-Dist: pytest>=8.4.1; extra == 'test'
